keypartx/KeypartX.py
keypartx/KeypartX_12.10.2022.py
keypartx/__init__.py
keypartx/basemodes/__init__.py
keypartx/basemodes/avn_base.py
keypartx/basemodes/net_base.py
keypartx/basemodes/text_edges.py
keypartx-0.1.20.dist-info/LICENCE.txt
keypartx-0.1.20.dist-info/METADATA
keypartx-0.1.20.dist-info/WHEEL
keypartx-0.1.20.dist-info/top_level.txt
keypartx-0.1.20.dist-info/RECORD
