Metadata-Version: 2.1
Name: keypartx
Version: 0.1.20
Summary: A Graph-based Perception(Text) Representation
Home-page: https://github.com/pengKiina/KeypartX
Author: Peng Yang
Author-email: pyseptimo@outlook.com
License: MIT
Keywords: text representation,text mining,nlp,topic modeling,emoji,image,perception
Classifier: Development Status :: 5 - Production/Stable
Classifier: Intended Audience :: Education
Classifier: Operating System :: Microsoft :: Windows :: Windows 11
Classifier: License :: OSI Approved :: MIT License
Classifier: Programming Language :: Python :: 3
License-File: LICENCE.txt
Requires-Dist: networkx
Requires-Dist: leidenalg
Requires-Dist: autocorrect
Requires-Dist: xlsxwriter
Requires-Dist: igraph
Requires-Dist: matplotlib
Requires-Dist: numpy
Requires-Dist: emoji
Provides-Extra: coreferee_spacy
Requires-Dist: coreferee ; extra == 'coreferee_spacy'
Requires-Dist: spacy (<3.4.1,>=3.0.0) ; extra == 'coreferee_spacy'
Provides-Extra: crosslingual-coreference_spacy
Requires-Dist: crosslingual-coreference ; extra == 'crosslingual-coreference_spacy'
Requires-Dist: spacy ; extra == 'crosslingual-coreference_spacy'
